commandfrog/__init__.py
commandfrog/commandfrog.spec
commandfrog/config.py
commandfrog/drivers/__init__.py
commandfrog/drivers/docker.py
commandfrog/drivers/driver.py
commandfrog/drivers/exceptions.py
commandfrog/drivers/local.py
commandfrog/drivers/ssh.py
commandfrog/drivers/util.py
commandfrog/operations/-
commandfrog/operations/__init__.py
commandfrog/operations/apt.py
commandfrog/operations/docker.py
commandfrog/operations/files.py
commandfrog/operations/git.py
commandfrog/operations/mongo.py
commandfrog/operations/nvm.py
commandfrog/operations/pacman.py
commandfrog/operations/platform.py
commandfrog/operations/pyenv.py
commandfrog/operations/shell.py
commandfrog/operations/ssh.py
commandfrog/operations/ubuntu.py
commandfrog/run.py
commandfrog/run.spec
commandfrog/utils.py
commandfrog-0.3.1.dist-info/entry_points.txt
commandfrog-0.3.1.dist-info/LICENSE
commandfrog-0.3.1.dist-info/WHEEL
commandfrog-0.3.1.dist-info/METADATA
commandfrog-0.3.1.dist-info/RECORD
